setup.py
meeseng_server.egg-info/PKG-INFO
meeseng_server.egg-info/SOURCES.txt
meeseng_server.egg-info/dependency_links.txt
meeseng_server.egg-info/requires.txt
meeseng_server.egg-info/top_level.txt
server/__init__.py
server/server.py
server/common/__init__.py
server/common/decos.py
server/common/descriptors.py
server/common/errors.py
server/common/metaclasses.py
server/common/utils.py
server/common/variables.py
server/logs/__init__.py
server/logs/server_log_config.py
server/servers/__init__.py
server/servers/database.py
server/servers/server_gui.py