Metadata-Version: 1.0
Name: meeseng-server
Version: 0.0.1
Summary: meeseng_server
Home-page: UNKNOWN
Author: Simakin Sergey
Author-email: sergeysimakin@gmail.com
License: UNKNOWN
Platform: UNKNOWN
